example_package/__init__.py
example_package/example.py
test_raasalghul-0.0.1.dist-info/LICENSE.txt
test_raasalghul-0.0.1.dist-info/METADATA
test_raasalghul-0.0.1.dist-info/WHEEL
test_raasalghul-0.0.1.dist-info/top_level.txt
test_raasalghul-0.0.1.dist-info/RECORD
