Metadata-Version: 2.1
Name: test-raasalghul
Version: 0.0.1
Summary: This package is used for event handling with dynamodb and SQS
Home-page: UNKNOWN
Author: Sathish Kumar Krisnamoorthy
Author-email: k.sathishrsurya@gmail.com
License: UNKNOWN
Platform: UNKNOWN
Classifier: Programming Language :: Python :: 3
Classifier: License :: OSI Approved :: MIT License
Classifier: Operating System :: OS Independent
Requires-Python: >=3.6
License-File: LICENSE.txt
